vinecopulas/__init__.py
vinecopulas/bivariate.py
vinecopulas/marginals.py
vinecopulas/vinecopula.py
VineCopulas-2.0.2.dist-info/LICENSE
VineCopulas-2.0.2.dist-info/METADATA
VineCopulas-2.0.2.dist-info/WHEEL
VineCopulas-2.0.2.dist-info/top_level.txt
VineCopulas-2.0.2.dist-info/RECORD
