Metadata-Version: 2.1
Name: VineCopulas
Version: 2.0.2
Author-email: Judith Claassen <j.n.claassen@vu.nl>
License: GNU GENERAL PUBLIC LICENSE Version 3
Project-URL: Homepage, https://github.com/IVM-VU/VineCopulas
Project-URL: Documentation, https://vinecopulas.readthedocs.io/en/latest/
Classifier: License :: OSI Approved :: MIT License
Classifier: Programming Language :: Python
Classifier: Operating System :: OS Independent
Classifier: Topic :: Scientific/Engineering :: GIS
Classifier: Topic :: Utilities
Requires-Python: >=3.9
License-File: LICENSE
Requires-Dist: numpy
Requires-Dist: scipy
Requires-Dist: numpy
Requires-Dist: pandas
Requires-Dist: matplotlib
Requires-Dist: networkx
Provides-Extra: tests
Requires-Dist: pytest; extra == "tests"
Provides-Extra: docs
Requires-Dist: jupyter; extra == "docs"
